nonebot_plugin_game_torrent-0.2.4.dist-info/METADATA
nonebot_plugin_game_torrent-0.2.4.dist-info/WHEEL
nonebot_plugin_game_torrent-0.2.4.dist-info/entry_points.txt
nonebot_plugin_game_torrent-0.2.4.dist-info/licenses/LICENCE
nonebot_plugin_game_torrent/__init__.py
nonebot_plugin_game_torrent/__main__.py
nonebot_plugin_game_torrent/config.py
nonebot_plugin_game_torrent/exception.py
nonebot_plugin_game_torrent/fetcher/__init__.py
nonebot_plugin_game_torrent/fetcher/aimhaven.py
nonebot_plugin_game_torrent/fetcher/base_model.py
nonebot_plugin_game_torrent/fetcher/fitgirl.py
nonebot_plugin_game_torrent/hook.py
nonebot_plugin_game_torrent/utils.py
nonebot_plugin_game_torrent-0.2.4.dist-info/RECORD
