Metadata-Version: 2.1
Name: nonebot-plugin-game-torrent
Version: 0.2.4
Summary: NoneBot 插件 - 游戏磁力链接查询 Aimheaven
Author: Cvandia
Author-Email: Cvandia <106718176+Cvandia@users.noreply.github.com>
License: MIT
Requires-Python: >=3.10
Requires-Dist: httpx>=0.27.0
Requires-Dist: fake-useragent<2.0.0,>=1.1.3
Requires-Dist: nonebot-plugin-waiter>=0.6.2
Requires-Dist: bs4<1.0.0,>=0.0.2
Requires-Dist: nonebot2>=2.2.0
Requires-Dist: qrcode>=8.0
Requires-Dist: nonebot-plugin-alconna>=0.55.0
